ktuvitDownloader/CustomExceptions.py
ktuvitDownloader/__init__.py
ktuvitDownloader/__main__.py
ktuvitDownloader/__version__.py
ktuvitDownloader/const.py
ktuvitDownloader/downloader.py
ktuvitDownloader/files.py
ktuvitDownloader/options.py
ktuvitDownloader/progress_bar.py
ktuvitDownloader-4.0.2.dist-info/DESCRIPTION.rst
ktuvitDownloader-4.0.2.dist-info/METADATA
ktuvitDownloader-4.0.2.dist-info/RECORD
ktuvitDownloader-4.0.2.dist-info/WHEEL
ktuvitDownloader-4.0.2.dist-info/entry_points.txt
ktuvitDownloader-4.0.2.dist-info/metadata.json
ktuvitDownloader-4.0.2.dist-info/top_level.txt
ktuvitDownloader-4.0.2.dist-info/zip-safe
