Metadata-Version: 2.0
Name: ktuvitDownloader
Version: 4.0.2
Summary: This package will allow you to auto-download subtitles from wizdom.xyz website.
Home-page: https://github.com/aviadlevy/ktuvitDownloader/
Author: Aviad Levy
Author-email: aviadlevy1@gmail.com
License: LGPLv3
Platform: UNKNOWN
Classifier: Development Status :: 5 - Production/Stable
Classifier: License :: OSI Approved :: GNU Library or Lesser General Public License (LGPL)
Classifier: Operating System :: OS Independent
Classifier: Intended Audience :: End Users/Desktop
Classifier: Programming Language :: Python :: 2
Classifier: Programming Language :: Python :: 3
Classifier: Topic :: Multimedia
Requires-Dist: appdirs
Requires-Dist: guessit
Requires-Dist: imdbpie
Requires-Dist: requests
Requires-Dist: pyyaml
Requires-Dist: six
